step_criterion/__init__.py
step_criterion/stepwise.py
step_criterion-0.2.2.dist-info/licenses/LICENSE
step_criterion-0.2.2.dist-info/METADATA
step_criterion-0.2.2.dist-info/WHEEL
step_criterion-0.2.2.dist-info/top_level.txt
step_criterion-0.2.2.dist-info/RECORD
