Metadata-Version: 2.4
Name: step-criterion
Version: 0.2.2
Summary: Educational stepwise model selection for statsmodels: AIC, BIC, Adjusted R², and p-values with OLS/GLM support for exploratory analysis.
Author-email: Mikael Hillman-Pepin <mikmik1512@gmail.com>
License: MIT
Project-URL: Homepage, https://github.com/MrRolie/step-criterion
Project-URL: Repository, https://github.com/MrRolie/step-criterion
Project-URL: Issues, https://github.com/MrRolie/step-criterion/issues
Project-URL: Documentation, https://github.com/MrRolie/step-criterion#readme
Keywords: statistics,regression,model-selection,stepwise,aic,bic,statsmodels,machine-learning
Classifier: Development Status :: 4 - Beta
Classifier: Intended Audience :: Science/Research
Classifier: Intended Audience :: Developers
Classifier: License :: OSI Approved :: MIT License
Classifier: Operating System :: OS Independent
Classifier: Programming Language :: Python :: 3
Classifier: Programming Language :: Python :: 3.9
Classifier: Programming Language :: Python :: 3.10
Classifier: Programming Language :: Python :: 3.11
Classifier: Programming Language :: Python :: 3.12
Classifier: Topic :: Scientific/Engineering :: Information Analysis
Classifier: Topic :: Scientific/Engineering :: Mathematics
Classifier: Topic :: Software Development :: Libraries :: Python Modules
Requires-Python: >=3.9
License-File: LICENSE
Requires-Dist: numpy>=1.23
Requires-Dist: pandas>=1.5
Requires-Dist: statsmodels>=0.13
Provides-Extra: dev
Requires-Dist: pytest>=6.0; extra == "dev"
Requires-Dist: jupyter>=1.0; extra == "dev"
Requires-Dist: black>=22.0; extra == "dev"
Requires-Dist: flake8>=4.0; extra == "dev"
Dynamic: license-file
